[{"keyword":"Feature","type":"feature","description":"","line":1,"name":"Search for an article on Wikipedia","uri":"/Users/serhataydin/wikitest/features/wiki.search.feature","tags":[],"elements":[{"keyword":"Scenario","type":"scenario","description":"","name":"We should find one article and land on its page","tags":[],"id":"search-for-an-article-on-wikipediawe-should-find-one-article-and-land-on-its-page","steps":[{"arguments":[],"keyword":"Before","name":"","result":{"status":"passed","duration":1000000},"line":null,"match":{"location":"can not be determined with webdriver.io"}},{"arguments":[],"keyword":"Given","name":"I open web browser for wikipedia;","result":{"status":"passed","duration":2000000},"line":null,"match":{"location":"can not be determined with webdriver.io"}},{"arguments":[],"keyword":"When","name":"I type \"Nicola Tesla\" on the search box","result":{"status":"passed","duration":2587000000},"line":null,"match":{"location":"can not be determined with webdriver.io"}},{"arguments":[],"keyword":"Then","name":"I click on search button","result":{"status":"passed","duration":2375000000},"line":null,"match":{"location":"can not be determined with webdriver.io"}},{"arguments":[],"keyword":"Then","name":"the URL should be \"https://en.wikipedia.org/wiki/Nikola_Tesla\";","result":{"status":"passed","duration":1007000000},"line":null,"match":{"location":"can not be determined with webdriver.io"}},{"arguments":[],"keyword":"Then","name":"I want to see an image under title \"Nikola Tesla\" on the right column","result":{"status":"passed","duration":60000000},"line":null,"match":{"location":"can not be determined with webdriver.io"}},{"arguments":[],"keyword":"Then","name":"I want to read information about \"Born\", \"Died\", \"Education\" on the right column","result":{"status":"failed","duration":10056000000,"error_message":"Error: Can't call getText on element with selector \"//th[contains(text(),'Education')]/../td\" because element wasn't found\n    at implicitWait (file:///Users/serhataydin/wikitest/node_modules/webdriverio/build/utils/implicitWait.js:29:19)\n    at Element.elementErrorHandlerCallbackFn (file:///Users/serhataydin/wikitest/node_modules/webdriverio/build/middlewares.js:14:29)\n    at Element.wrapCommandFn (file:///Users/serhataydin/wikitest/node_modules/@wdio/utils/build/shim.js:81:29)\n    at ArticlePage.getHeaderText (/Users/serhataydin/wikitest/features/pageobjects/article.page.js:32:18)\n    at World.<anonymous> (/Users/serhataydin/wikitest/features/step-definitions/wiki.search.steps.js:45:5)"},"line":null,"match":{"location":"can not be determined with webdriver.io"}},{"arguments":[],"keyword":"Then","name":"I want to read a section about \"Early years\"","result":{"status":"skipped","duration":0},"line":null,"match":{"location":"can not be determined with webdriver.io"}},{"arguments":[],"keyword":"After","name":"","result":{"status":"passed","duration":0},"line":null,"match":{"location":"can not be determined with webdriver.io"}}]}],"id":"search-for-an-article-on-wikipedia","metadata":{"browser":{"name":"chrome","version":"127.0.6533.120"},"device":"Device name not known","platform":{"name":"osx","version":"Version not known"}}}]
